{
  "unversionedId": "adapter/schemas",
  "id": "adapter/schemas",
  "isDocsHomePage": false,
  "title": "Schemas",
  "description": "Introduction",
  "source": "@site/docs/adapter/schemas.md",
  "sourceDirName": "adapter",
  "slug": "/adapter/schemas",
  "permalink": "/openfmb.docs/docs/adapter/schemas",
  "editUrl": "https://github.com/openenergysolutions/openfmb.docs/edit/develop/website/docs/adapter/schemas.md",
  "version": "current",
  "sidebarPosition": 4,
  "frontMatter": {
    "sidebar_position": 4
  },
  "sidebar": "tutorialSidebar",
  "previous": {
    "title": "CLI",
    "permalink": "/openfmb.docs/docs/adapter/cli"
  },
  "next": {
    "title": "Configuration",
    "permalink": "/openfmb.docs/docs/adapter/config"
  }
}